[
  { "name": "Bank Central Asia", "code": "014", "alias": "BCA" },
  { "name": "Bank Mandiri", "code": "008", "alias": "Mandiri" },
  { "name": "Bank Negara Indonesia", "code": "009", "alias": "BNI" },
  { "name": "Bank Rakyat Indonesia", "code": "002", "alias": "BRI" },
  { "name": "Bank Tabungan Negara", "code": "200", "alias": "BTN" },
  { "name": "Bank CIMB Niaga", "code": "022", "alias": "CIMB" },
  { "name": "Bank Syariah Indonesia", "code": "451", "alias": "BSI" },
  { "name": "Bank Muamalat Indonesia", "code": "147", "alias": "Muamalat" },
  { "name": "Bank Tabungan Pensiunan Nasional", "code": "213", "alias": "BTPN" },
  { "name": "Jenius", "code": "213", "alias": "Jenius" },
  { "name": "Permata Bank", "code": "013", "alias": "Permata" },
  { "name": "Bank Danamon", "code": "011", "alias": "Danamon" },
  { "name": "Bank Maybank Indonesia", "code": "016", "alias": "Maybank" },
  { "name": "Bank Mega", "code": "426", "alias": "Mega" },
  { "name": "Bank Sinarmas", "code": "153", "alias": "Sinarmas" },
  { "name": "Bank OCBC NISP", "code": "028", "alias": "OCBC" },
  { "name": "Bank Bukopin", "code": "441", "alias": "Bukopin" },
  { "name": "Citibank", "code": "031", "alias": "Citi" },
  { "name": "Bank DBS Indonesia", "code": "046", "alias": "DBS" },
  { "name": "Bank Neo Commerce", "code": "490", "alias": "Neo" },
  { "name": "Allo Bank", "code": "567", "alias": "Allo" },
  { "name": "SeaBank", "code": "535", "alias": "SeaBank" },
  { "name": "Bank Jago", "code": "542", "alias": "Jago" },
  { "name": "Bank UOB Indonesia", "code": "023", "alias": "UOB" },
  { "name": "Standard Chartered Bank", "code": "050", "alias": "Standard Chartered" },
  { "name": "HSBC Indonesia", "code": "087", "alias": "HSBC" },
  { "name": "Bank Victoria International", "code": "566", "alias": "Victoria" },
  { "name": "Bank Aladin Syariah", "code": "947", "alias": "Aladin" },
  { "name": "Bank BCA Syariah", "code": "536", "alias": "BCA Syariah" },
  { "name": "Bank Panin Dubai Syariah", "code": "517", "alias": "Panin Syariah" },
  { "name": "Bank BJB", "code": "110", "alias": "BJB" },
  { "name": "Bank DKI", "code": "111", "alias": "DKI" },
  { "name": "Bank Jatim", "code": "114", "alias": "Jatim" },
  { "name": "Bank Jateng", "code": "113", "alias": "Jateng" },
  { "name": "Bank Sumut", "code": "117", "alias": "Sumut" },
  { "name": "Bank Nagari", "code": "118", "alias": "Nagari" },
  { "name": "Bank Sumsel Babel", "code": "120", "alias": "Sumsel Babel" },
  { "name": "Bank Kalbar", "code": "123", "alias": "Kalbar" },
  { "name": "Bank Kalsel", "code": "122", "alias": "Kalsel" },
  { "name": "Bank Papua", "code": "132", "alias": "Papua" },
  { "name": "Bank Aceh", "code": "116", "alias": "Aceh" }
]
